xiaoapi_mongodb/__init__.py
xiaoapi_mongodb/mongo_manage.py
xiaoapi_mongodb/mongodb.py
xiaoapi_mongodb-0.0.3.dist-info/LICENSE
xiaoapi_mongodb-0.0.3.dist-info/METADATA
xiaoapi_mongodb-0.0.3.dist-info/WHEEL
xiaoapi_mongodb-0.0.3.dist-info/top_level.txt
xiaoapi_mongodb-0.0.3.dist-info/RECORD
