Metadata-Version: 2.1
Name: xiaoapi-mongodb
Version: 0.0.3
Summary: xiaoapi mongodb
Author-email: xiaojinli <553555614@qq.com>
License: MIT
Project-URL: Documentation, https://github.com/xiaojinlii/xiaoapi/blob/main/libs/mongodb/README.md
Project-URL: Repository, https://github.com/xiaojinlii/xiaoapi
Project-URL: Source Code, https://github.com/xiaojinlii/xiaoapi/tree/main/libs/mongodb
Keywords: xiaoapi,fastapi,web-framework,mongodb
Classifier: Framework :: FastAPI
Classifier: Programming Language :: Python :: 3
Requires-Python: >=3.8
License-File: LICENSE
Requires-Dist: xiaoapi >=0.0.2
Requires-Dist: motor ==3.3.2
